kahip-3.22.dist-info/RECORD
kahip-3.22.dist-info/WHEEL
kahip-3.22.dist-info/METADATA
kahip-3.22.dist-info/licenses/LICENSE
bin/node_ordering
bin/evaluator
bin/interface_test
bin/kaffpa
bin/edge_evaluator
bin/node_separator
bin/partition_to_vertex_separator
bin/edge_partitioning
bin/label_propagation
bin/global_multisection
bin/graphchecker
include/kaHIP_interface.h
lib/libkahip.dylib
lib/libkahip_static.a
kahip/_version.py
kahip/kahip.cpython-39-darwin.so
kahip/__init__.py
